shuttleai/__init__.py
shuttleai/_patch.py
shuttleai/_types.py
shuttleai/cli/__init__.py
shuttleai/cli/__main__.py
shuttleai/client/__init__.py
shuttleai/client/_async.py
shuttleai/client/_sync.py
shuttleai/client/base.py
shuttleai/exceptions.py
shuttleai/helpers.py
shuttleai/py.typed
shuttleai/resources/__init__.py
shuttleai/resources/audio/audio.py
shuttleai/resources/audio/speech.py
shuttleai/resources/audio/transcriptions.py
shuttleai/resources/audio/translations.py
shuttleai/resources/chat/completions.py
shuttleai/resources/common.py
shuttleai/resources/embeddings.py
shuttleai/resources/etc/insults.py
shuttleai/resources/etc/jokes.py
shuttleai/resources/etc/web_search.py
shuttleai/resources/images/generations.py
shuttleai/resources/moderations.py
shuttleai/resources/video/generations.py
shuttleai/schemas/__init__.py
shuttleai/schemas/audio/speech.py
shuttleai/schemas/audio/transcriptions.py
shuttleai/schemas/audio/translations.py
shuttleai/schemas/chat/completions.py
shuttleai/schemas/common.py
shuttleai/schemas/embeddings.py
shuttleai/schemas/etc/insults.py
shuttleai/schemas/etc/jokes.py
shuttleai/schemas/etc/web_search.py
shuttleai/schemas/images/generations.py
shuttleai/schemas/models/__init__.py
shuttleai/schemas/models/capabilities.py
shuttleai/schemas/models/models.py
shuttleai/schemas/moderations.py
shuttleai/schemas/video/generations.py
shuttleai-4.8.1.dist-info/entry_points.txt
shuttleai-4.8.1.dist-info/LICENSE
shuttleai-4.8.1.dist-info/METADATA
shuttleai-4.8.1.dist-info/WHEEL
shuttleai-4.8.1.dist-info/RECORD
