Metadata-Version: 2.1
Name: shuttleai
Version: 4.8.1
Summary: Access Shuttle AI's API via an easy-to-use Python wrapper. Dashboard: https://shuttleai.com Discord: https://discord.gg/shuttleai
Home-page: https://github.com/shuttleai
Keywords: shuttleai,ai,gpt,claude,api,free,chatgpt,gpt-4
Author: Tristan Liu
Author-email: tristan@shuttleai.app
Maintainer: Christian "Thoth" Heru
Maintainer-email: chris@shuttleai.app
Requires-Python: >=3.9,<4.0
Classifier: License :: OSI Approved :: MIT License
Classifier: Operating System :: OS Independent
Classifier: Programming Language :: Python :: 3
Classifier: Programming Language :: Python :: 3.9
Classifier: Programming Language :: Python :: 3.10
Classifier: Programming Language :: Python :: 3.11
Classifier: Programming Language :: Python :: 3.12
Requires-Dist: aiofiles (>=23.2.1,<24.0.0)
Requires-Dist: aiohttp (>=3.9.5,<4.0.0)
Requires-Dist: httpx (>=0.25.2,<1)
Requires-Dist: matplotlib (>=3.9.0,<4.0.0)
Requires-Dist: orjson (>=3.10.3,<4.0.0)
Requires-Dist: poetry-version-plugin (>=0.2.0,<0.3.0)
Requires-Dist: pydantic (>=2.7.3,<3.0.0)
Requires-Dist: pyreadline3 (>=3.4.1,<4.0.0)
Requires-Dist: python-dateutil (>=2.9.0.post0,<3.0.0)
Requires-Dist: types-aiofiles (>=23.2.0.20240403,<24.0.0.0)
Project-URL: Documentation, https://docs.shuttleai.com
Project-URL: Dashboard, https://shuttleai.com
Project-URL: Discord, https://discord.gg/shuttleai
Project-URL: PyPI, https://pypi.org/project/shuttleai
Project-URL: Repository, https://github.com/shuttleai/shuttleai-python
